{"nodes": [{"id": "apps_web_app_projects_views_tsx", "label": "_views.tsx", "file_type": "code", "source_file": "apps/web/app/projects/_views.tsx", "source_location": "L1"}, {"id": "views_mk", "label": "mk()", "file_type": "code", "source_file": "apps/web/app/projects/_views.tsx", "source_location": "L13"}, {"id": "views_handleprojectcreated", "label": "handleProjectCreated()", "file_type": "code", "source_file": "apps/web/app/projects/_views.tsx", "source_location": "L520"}], "edges": [{"source": "apps_web_app_projects_views_tsx", "target": "react", "relation": "imports_from", "confidence": "EXTRACTED", "source_file": "apps/web/app/projects/_views.tsx", "source_location": "L3", "weight": 1.0}, {"source": "apps_web_app_projects_views_tsx", "target": "navigation", "relation": "imports_from", "confidence": "EXTRACTED", "source_file": "apps/web/app/projects/_views.tsx", "source_location": "L4", "weight": 1.0}, {"source": "apps_web_app_projects_views_tsx", "target": "apps_web_app_projects_projects_css", "relation": "imports_from", "confidence": "EXTRACTED", "source_file": "apps/web/app/projects/_views.tsx", "source_location": "L5", "weight": 1.0}, {"source": "apps_web_app_projects_views_tsx", "target": "ogsidebar", "relation": "imports_from", "confidence": "EXTRACTED", "source_file": "apps/web/app/projects/_views.tsx", "source_location": "L6", "weight": 1.0}, {"source": "apps_web_app_projects_views_tsx", "target": "projectslistsidebar", "relation": "imports_from", "confidence": "EXTRACTED", "source_file": "apps/web/app/projects/_views.tsx", "source_location": "L7", "weight": 1.0}, {"source": "apps_web_app_projects_views_tsx", "target": "projectstore", "relation": "imports_from", "confidence": "EXTRACTED", "source_file": "apps/web/app/projects/_views.tsx", "source_location": "L8", "weight": 1.0}, {"source": "apps_web_app_projects_views_tsx", "target": "views_mk", "relation": "contains", "confidence": "EXTRACTED", "source_file": "apps/web/app/projects/_views.tsx", "source_location": "L13", "weight": 1.0}, {"source": "apps_web_app_projects_views_tsx", "target": "views_handleprojectcreated", "relation": "contains", "confidence": "EXTRACTED", "source_file": "apps/web/app/projects/_views.tsx", "source_location": "L520", "weight": 1.0}], "raw_calls": [{"caller_nid": "views_handleprojectcreated", "callee": "addProject", "source_file": "apps/web/app/projects/_views.tsx", "source_location": "L522"}, {"caller_nid": "views_handleprojectcreated", "callee": "push", "source_file": "apps/web/app/projects/_views.tsx", "source_location": "L523"}]}